textstat/__init__.py
textstat/textstat.py
textstat/resources/en/easy_words.txt
textstat/resources/es/easy_words.txt
whylabs_textstat-0.7.4.dist-info/LICENSE
whylabs_textstat-0.7.4.dist-info/METADATA
whylabs_textstat-0.7.4.dist-info/WHEEL
whylabs_textstat-0.7.4.dist-info/top_level.txt
whylabs_textstat-0.7.4.dist-info/RECORD
